poly_query_mcp/__init__.py
poly_query_mcp/server.py
poly_query_mcp/databases/__init__.py
poly_query_mcp/databases/base.py
poly_query_mcp/databases/mongodb_connection.py
poly_query_mcp/databases/mysql_connection.py
poly_query_mcp/databases/postgresql_connection.py
poly_query_mcp/databases/redis_connection.py
poly_query_mcp/utils/__init__.py
poly_query_mcp/utils/config.json
poly_query_mcp/utils/config.py
poly_query_mcp/utils/config_manager.py
poly_query_mcp/utils/enhanced_config.py
poly_query_mcp/utils/enhanced_config_manager.py
poly_query_mcp/utils/exceptions.py
poly_query_mcp/utils/logger.py
poly_query_mcp-0.1.0.dist-info/METADATA
poly_query_mcp-0.1.0.dist-info/WHEEL
poly_query_mcp-0.1.0.dist-info/entry_points.txt
poly_query_mcp-0.1.0.dist-info/licenses/LICENSE
poly_query_mcp-0.1.0.dist-info/RECORD
