Metadata-Version: 2.4
Name: poly-query-mcp
Version: 0.1.0
Summary: MCP tool for connecting to MySQL, PostgreSQL, Redis and MongoDB databases
Project-URL: Homepage, https://github.com/yourusername/poly-query-mcp
Project-URL: Documentation, https://github.com/yourusername/poly-query-mcp/docs
Project-URL: Repository, https://github.com/yourusername/poly-query-mcp.git
Project-URL: Bug Tracker, https://github.com/yourusername/poly-query-mcp/issues
Author-email: Your Name <your.email@example.com>
License: MIT
License-File: LICENSE
Keywords: database,mcp,mongodb,mysql,postgresql,query,redis
Classifier: Development Status :: 4 - Beta
Classifier: Intended Audience :: Developers
Classifier: License :: OSI Approved :: MIT License
Classifier: Programming Language :: Python :: 3
Classifier: Programming Language :: Python :: 3.12
Classifier: Programming Language :: Python :: 3.13
Classifier: Topic :: Database
Classifier: Topic :: Software Development :: Libraries :: Python Modules
Requires-Python: >=3.12
Requires-Dist: mcp>=1.0.0
Requires-Dist: psycopg2-binary>=2.9.9
Requires-Dist: pydantic>=2.5.0
Requires-Dist: pymongo>=4.6.0
Requires-Dist: pymysql>=1.1.0
Requires-Dist: python-dotenv>=1.0.0
Requires-Dist: redis>=5.0.1
Provides-Extra: dev
Requires-Dist: black>=23.0.0; extra == 'dev'
Requires-Dist: flake8>=6.0.0; extra == 'dev'
Requires-Dist: isort>=5.12.0; extra == 'dev'
Requires-Dist: mypy>=1.0.0; extra == 'dev'
Requires-Dist: pytest-asyncio>=0.21.0; extra == 'dev'
Requires-Dist: pytest>=7.0.0; extra == 'dev'
